qui/__init__.py
qui/qui_.cp35-win_amd64.pyd
qui/Qt/bin/Qt5Core.dll
qui/Qt/bin/Qt5Gui.dll
qui/Qt/bin/Qt5Network.dll
qui/Qt/bin/Qt5Qml.dll
qui/Qt/bin/Qt5Quick.dll
qui/Qt/bin/Qt5QuickControls2.dll
qui/Qt/bin/Qt5QuickTemplates2.dll
qui/Qt/bin/Qt5Svg.dll
qui/Qt/bin/Qt5Widgets.dll
qui/Qt/bin/libEGL.dll
qui/Qt/bin/libGLESV2.dll
qui/Qt/plugins/bearer/qgenericbearer.dll
qui/Qt/plugins/iconengines/qsvgicon.dll
qui/Qt/plugins/imageformats/qgif.dll
qui/Qt/plugins/imageformats/qicns.dll
qui/Qt/plugins/imageformats/qico.dll
qui/Qt/plugins/imageformats/qjpeg.dll
qui/Qt/plugins/imageformats/qsvg.dll
qui/Qt/plugins/imageformats/qtga.dll
qui/Qt/plugins/imageformats/qtiff.dll
qui/Qt/plugins/imageformats/qwbmp.dll
qui/Qt/plugins/imageformats/qwebp.dll
qui/Qt/plugins/platforminputcontexts/qtvirtualkeyboardplugin.dll
qui/Qt/plugins/platforms/qwindows.dll
qui/Qt/plugins/qmltooling/qmldbg_debugger.dll
qui/Qt/plugins/qmltooling/qmldbg_inspector.dll
qui/Qt/plugins/qmltooling/qmldbg_local.dll
qui/Qt/plugins/qmltooling/qmldbg_messages.dll
qui/Qt/plugins/qmltooling/qmldbg_native.dll
qui/Qt/plugins/qmltooling/qmldbg_nativedebugger.dll
qui/Qt/plugins/qmltooling/qmldbg_profiler.dll
qui/Qt/plugins/qmltooling/qmldbg_quickprofiler.dll
qui/Qt/plugins/qmltooling/qmldbg_server.dll
qui/Qt/plugins/qmltooling/qmldbg_tcp.dll
qui/Qt/plugins/scenegraph/qsgd3d12backend.dll
qui/Qt/plugins/styles/qwindowsvistastyle.dll
qui/Qt/qml/builtins.qmltypes
qui/Qt/qml/Qt/WebSockets/qmldir
qui/Qt/qml/Qt/labs/calendar/DayOfWeekRow.qml
qui/Qt/qml/Qt/labs/calendar/DayOfWeekRow.qmlc
qui/Qt/qml/Qt/labs/calendar/MonthGrid.qml
qui/Qt/qml/Qt/labs/calendar/MonthGrid.qmlc
qui/Qt/qml/Qt/labs/calendar/WeekNumberColumn.qml
qui/Qt/qml/Qt/labs/calendar/WeekNumberColumn.qmlc
qui/Qt/qml/Qt/labs/calendar/plugins.qmltypes
qui/Qt/qml/Qt/labs/calendar/qmldir
qui/Qt/qml/Qt/labs/calendar/qtlabscalendarplugin.dll
qui/Qt/qml/Qt/labs/calendar/qtlabscalendarplugind.dll
qui-1.0.2.dist-info/METADATA
qui-1.0.2.dist-info/RECORD
qui-1.0.2.dist-info/WHEEL
qui-1.0.2.dist-info/top_level.txt
